linktune/__init__.py
linktune/cli.py
linktune/blocks/__init__.py
linktune/blocks/langfuse_integration.py
linktune/blocks/ai/__init__.py
linktune/blocks/ai/chatgpt.py
linktune/blocks/ai/chatmusician.py
linktune/blocks/ai/claude.py
linktune/blocks/neural/__init__.py
linktune/blocks/neural/harmony.py
linktune/blocks/neural/orpheus_bridge.py
linktune/core/__init__.py
linktune/core/analyzer.py
linktune/core/clipboard.py
linktune/core/converter.py
linktune/core/extractor.py
linktune/core/generator.py
linktune/core/lego_factory.py
linktune/core/pipeline.py
linktune/utils/__init__.py
linktune/utils/registry.py
link2abc-0.3.0.dist-info/METADATA
link2abc-0.3.0.dist-info/WHEEL
link2abc-0.3.0.dist-info/entry_points.txt
link2abc-0.3.0.dist-info/licenses/LICENSE
link2abc-0.3.0.dist-info/RECORD
