Metadata-Version: 2.4
Name: link2abc
Version: 0.3.0
Summary: Transform any link or clipboard content into music with AI - mobile-friendly!
Project-URL: Homepage, https://github.com/jgwill/link2abc
Project-URL: Documentation, https://link2abc.readthedocs.io
Project-URL: Repository, https://github.com/jgwill/link2abc
Project-URL: Issues, https://github.com/jgwill/link2abc/issues
Project-URL: Changelog, https://github.com/jgwill/link2abc/blob/main/CHANGELOG.md
Author-email: gerico1007 <gerico@jgwill.com>
License: MIT
License-File: LICENSE
Keywords: abc,ai,chatmusician,link-to-abc,music,notation,orpheus,web-to-music
Classifier: Development Status :: 4 - Beta
Classifier: Intended Audience :: Developers
Classifier: Intended Audience :: End Users/Desktop
Classifier: License :: OSI Approved :: MIT License
Classifier: Operating System :: OS Independent
Classifier: Programming Language :: Python :: 3
Classifier: Programming Language :: Python :: 3.8
Classifier: Programming Language :: Python :: 3.9
Classifier: Programming Language :: Python :: 3.10
Classifier: Programming Language :: Python :: 3.11
Classifier: Programming Language :: Python :: 3.12
Classifier: Topic :: Artistic Software
Classifier: Topic :: Internet :: WWW/HTTP
Classifier: Topic :: Multimedia :: Sound/Audio
Requires-Python: >=3.8
Requires-Dist: beautifulsoup4>=4.9.0
Requires-Dist: click>=8.0.0
Requires-Dist: music21>=8.1.0
Requires-Dist: pydantic>=2.0.0
Requires-Dist: pyyaml>=6.0.0
Requires-Dist: requests>=2.25.0
Provides-Extra: ai
Requires-Dist: anthropic>=0.18.0; extra == 'ai'
Requires-Dist: langfuse>=2.0.0; extra == 'ai'
Requires-Dist: openai>=1.0.0; extra == 'ai'
Provides-Extra: cloud
Requires-Dist: boto3>=1.26.0; extra == 'cloud'
Requires-Dist: google-cloud-compute>=1.11.0; extra == 'cloud'
Requires-Dist: redis>=4.0.0; extra == 'cloud'
Provides-Extra: dev
Requires-Dist: black>=23.0.0; extra == 'dev'
Requires-Dist: mypy>=1.0.0; extra == 'dev'
Requires-Dist: pre-commit>=3.0.0; extra == 'dev'
Requires-Dist: pytest-cov>=4.0.0; extra == 'dev'
Requires-Dist: pytest>=7.0.0; extra == 'dev'
Requires-Dist: ruff>=0.1.0; extra == 'dev'
Provides-Extra: full
Requires-Dist: anthropic>=0.18.0; extra == 'full'
Requires-Dist: boto3>=1.26.0; extra == 'full'
Requires-Dist: google-cloud-compute>=1.11.0; extra == 'full'
Requires-Dist: langfuse>=2.0.0; extra == 'full'
Requires-Dist: lxml>=4.6.0; extra == 'full'
Requires-Dist: openai>=1.0.0; extra == 'full'
Requires-Dist: redis>=4.0.0; extra == 'full'
Requires-Dist: symusic>=0.5.0; extra == 'full'
Requires-Dist: torch>=2.0.0; extra == 'full'
Requires-Dist: torchaudio>=2.0.0; extra == 'full'
Requires-Dist: vosk>=0.3.0; extra == 'full'
Provides-Extra: neural
Requires-Dist: symusic>=0.5.0; extra == 'neural'
Requires-Dist: torch>=2.0.0; extra == 'neural'
Requires-Dist: torchaudio>=2.0.0; extra == 'neural'
Requires-Dist: vosk>=0.3.0; extra == 'neural'
Provides-Extra: parsing
Requires-Dist: lxml>=4.6.0; extra == 'parsing'
